setup.py
probability_distribution_package/Binomialdistribution.py
probability_distribution_package/Gaussiandistribution.py
probability_distribution_package/Generaldistribution.py
probability_distribution_package/__init__.py
probability_distribution_package.egg-info/PKG-INFO
probability_distribution_package.egg-info/SOURCES.txt
probability_distribution_package.egg-info/dependency_links.txt
probability_distribution_package.egg-info/not-zip-safe
probability_distribution_package.egg-info/top_level.txt