Metadata-Version: 1.0
Name: probability-distribution-package
Version: 1.0
Summary: Gaussian and binomial distributions functions
Home-page: UNKNOWN
Author: Siddhesh Sanap
Author-email: siddheshsanap0002@gmail.com
License: UNKNOWN
Platform: UNKNOWN
